writio/__init__.py
writio-0.1.2.dist-info/LICENSE
writio-0.1.2.dist-info/METADATA
writio-0.1.2.dist-info/WHEEL
writio-0.1.2.dist-info/RECORD
