Metadata-Version: 2.1
Name: writio
Version: 0.1.2
Summary: A file reading and writing library for `.csv`, `.yaml`, `.json`, and `.pickle` files. You probably shouldn't use this.
License: MIT
Author: Florian Matter
Author-email: flmt@mailbox.org
Requires-Python: >=3.8,<4.0
Classifier: License :: OSI Approved :: MIT License
Classifier: Programming Language :: Python :: 3
Classifier: Programming Language :: Python :: 3.8
Classifier: Programming Language :: Python :: 3.9
Classifier: Programming Language :: Python :: 3.10
Classifier: Programming Language :: Python :: 3.11
Classifier: Programming Language :: Python :: 3.12
Requires-Dist: invoke (>=2.2.0,<3.0.0)
Requires-Dist: pyyaml (>=6.0.1,<7.0.0)
